cliqestimceshi/__init__.py
cliqestimceshi/main.cpython-311-darwin.so
cliqestimceshi/timer.cpython-311-darwin.so
cliqestimceshi-0.1.0.dist-info/LICENCE.txt
cliqestimceshi-0.1.0.dist-info/METADATA
cliqestimceshi-0.1.0.dist-info/WHEEL
cliqestimceshi-0.1.0.dist-info/top_level.txt
cliqestimceshi-0.1.0.dist-info/RECORD
